torchaudio/__init__.py
torchaudio/kaldi_io.py
torchaudio/version.py
torchaudio/_backend/__init__.py
torchaudio/_backend/utils.py
torchaudio/_extension/__init__.py
torchaudio/_extension/utils.py
torchaudio/_internal/__init__.py
torchaudio/_internal/module_utils.py
torchaudio/backend/__init__.py
torchaudio/backend/common.py
torchaudio/backend/no_backend.py
torchaudio/backend/soundfile_backend.py
torchaudio/backend/sox_io_backend.py
torchaudio/backend/utils.py
torchaudio/compliance/__init__.py
torchaudio/compliance/kaldi.py
torchaudio/datasets/__init__.py
torchaudio/datasets/cmuarctic.py
torchaudio/datasets/cmudict.py
torchaudio/datasets/commonvoice.py
torchaudio/datasets/dr_vctk.py
torchaudio/datasets/fluentcommands.py
torchaudio/datasets/gtzan.py
torchaudio/datasets/iemocap.py
torchaudio/datasets/librilight_limited.py
torchaudio/datasets/librimix.py
torchaudio/datasets/librispeech.py
torchaudio/datasets/librispeech_biasing.py
torchaudio/datasets/libritts.py
torchaudio/datasets/ljspeech.py
torchaudio/datasets/musdb_hq.py
torchaudio/datasets/quesst14.py
torchaudio/datasets/snips.py
torchaudio/datasets/speechcommands.py
torchaudio/datasets/tedlium.py
torchaudio/datasets/utils.py
torchaudio/datasets/vctk.py
torchaudio/datasets/voxceleb1.py
torchaudio/datasets/yesno.py
torchaudio/functional/__init__.py
torchaudio/functional/filtering.py
torchaudio/functional/functional.py
torchaudio/io/__init__.py
torchaudio/io/_compat.py
torchaudio/io/_effector.py
torchaudio/io/_playback.py
torchaudio/io/_stream_reader.py
torchaudio/io/_stream_writer.py
torchaudio/lib/_torchaudio.so
torchaudio/lib/_torchaudio_sox.so
torchaudio/lib/libctc_prefix_decoder.so
torchaudio/lib/libtorchaudio.so
torchaudio/lib/libtorchaudio_sox.so
torchaudio/lib/pybind11_prefixctc.so
torchaudio/models/__init__.py
torchaudio/models/_hdemucs.py
torchaudio/models/conformer.py
torchaudio/models/conv_tasnet.py
torchaudio/models/deepspeech.py
torchaudio/models/emformer.py
torchaudio/models/rnnt.py
gladia_torchaudio-2.1.0a0.dist-info/LICENSE
gladia_torchaudio-2.1.0a0.dist-info/METADATA
gladia_torchaudio-2.1.0a0.dist-info/WHEEL
gladia_torchaudio-2.1.0a0.dist-info/top_level.txt
gladia_torchaudio-2.1.0a0.dist-info/RECORD
